testuiop/__init__.py
testuiop-1.0.dist-info/METADATA
testuiop-1.0.dist-info/WHEEL
testuiop-1.0.dist-info/top_level.txt
testuiop-1.0.dist-info/RECORD
