Metadata-Version: 2.1
Name: testuiop
Version: 1.0
Summary: Testing something
Home-page: UNKNOWN
Author: Tector Pro
Author-email: UNKNOWN
License: UNKNOWN
Platform: UNKNOWN
